underdata/League.py
underdata/Match.py
underdata/Player.py
underdata/Team.py
underdata/__init__.py
underdata/client.py
underdata-0.2.0.dist-info/licenses/LICENSE
underdata-0.2.0.dist-info/METADATA
underdata-0.2.0.dist-info/WHEEL
underdata-0.2.0.dist-info/top_level.txt
underdata-0.2.0.dist-info/RECORD
