Metadata-Version: 2.4
Name: underdata
Version: 0.2.0
Summary: Scraping data package for www.understat.com
Home-page: https://github.com/osvaldomx/UnderData
Author: Osvaldo Trujillo
Author-email: osvaldo.trujillo.ingenieria@gmail.com
License: MIT
Classifier: License :: OSI Approved :: MIT License
Classifier: Programming Language :: Python
Classifier: Programming Language :: Python :: 3
Classifier: Programming Language :: Python :: 3.13
Classifier: Operating System :: OS Independent
Requires-Python: >=3.13
License-File: LICENSE
Requires-Dist: requests==2.32.3
Requires-Dist: beautifulsoup4==4.12.3
Requires-Dist: pandas==2.2.2
Dynamic: author
Dynamic: author-email
Dynamic: classifier
Dynamic: description
Dynamic: description-content-type
Dynamic: home-page
Dynamic: license
Dynamic: license-file
Dynamic: requires-dist
Dynamic: requires-python
Dynamic: summary
